{
  "_class": "group",
  "do_objectID": "88BA971F-A6B5-4C2A-8FB1-4132FBA65277",
  "exportOptions": {
    "_class": "exportOptions",
    "exportFormats": [
    ],
    "includedLayerIds": [
    ],
    "layerOptions": 0,
    "shouldTrim": false
  },
  "frame": {
    "_class": "rect",
    "constrainProportions": false,
    "height": 52,
    "width": 126,
    "x": 0,
    "y": 0
  },
  "hasClickThrough": false,
  "isFlippedHorizontal": false,
  "isFlippedVertical": false,
  "isLocked": false,
  "isVisible": true,
  "layerListExpandedType": 0,
  "layers": [
    {
      "class": "shapeGroup",
      "id": "2F620584-DD32-497C-B507-0C83DA27ACD8"
    },
    {
      "class": "text",
      "id": "873FCE7D-B5BF-48E1-BD38-DD2D0DFD090F"
    }
  ],
  "name": "Tooltip Top Dark",
  "nameIsFixed": true,
  "resizingConstraint": 63,
  "resizingType": 0,
  "rotation": 0,
  "shouldBreakMaskChain": false,
  "style": {
    "_class": "style",
    "endDecorationType": 0,
    "miterLimit": 10,
    "startDecorationType": 0
  }
}