{
  "_class": "group",
  "do_objectID": "A96344BD-E943-4C1D-9BB7-6176374D609B",
  "exportOptions": {
    "_class": "exportOptions",
    "exportFormats": [
    ],
    "includedLayerIds": [
    ],
    "layerOptions": 0,
    "shouldTrim": false
  },
  "frame": {
    "_class": "rect",
    "constrainProportions": false,
    "height": 36,
    "width": 300,
    "x": 0,
    "y": 0
  },
  "hasClickThrough": false,
  "isFlippedHorizontal": false,
  "isFlippedVertical": false,
  "isLocked": false,
  "isVisible": true,
  "layerListExpandedType": 2,
  "layers": [
    {
      "class": "symbolInstance",
      "id": "807272ED-4E58-4DBF-A39F-EE3DC3064578"
    },
    {
      "class": "group",
      "id": "2A806816-DC20-40B0-955E-34C834D5B316"
    },
    {
      "class": "text",
      "id": "E993B10B-F89E-491F-8227-1275183C1B59"
    },
    {
      "class": "symbolInstance",
      "id": "19C48616-19BF-462C-B63E-FF27F0B6C8EF"
    },
    {
      "class": "symbolInstance",
      "id": "634AC909-4ED9-4E74-A47F-312D9DE34B3E"
    },
    {
      "class": "symbolInstance",
      "id": "B4E77972-C894-4B28-871A-4AB70EB54F2D"
    }
  ],
  "name": "Input Error",
  "nameIsFixed": false,
  "resizingConstraint": 63,
  "resizingType": 0,
  "rotation": 0,
  "shouldBreakMaskChain": false,
  "style": {
    "_class": "style",
    "endDecorationType": 0,
    "miterLimit": 10,
    "startDecorationType": 0
  }
}